{
  "items": [
    {
      "title": "scikit-learn KNeighborsClassifier documentation",
      "url": "https://scikit-learn.org/stable/modules/generated/sklearn.neighbors.KNeighborsClassifier.html",
      "author": "scikit-learn developers",
      "note": "API for n_neighbors, metrics, weights, and tree-based algorithms for neighbor search."
    },
    {
      "title": "The Elements of Statistical Learning — Chapter 2.3 (k-Nearest-Neighbor Methods)",
      "url": "https://hastie.su.domains/ElemStatLearn/",
      "author": "Trevor Hastie, Robert Tibshirani, Jerome Friedman",
      "note": "Bias–variance of k, curse of dimensionality, and adaptive nearest neighbors."
    },
    {
      "title": "Pattern Recognition and Machine Learning — Section 2.5 (Constructing New Features)",
      "url": "https://www.microsoft.com/en-us/research/publication/pattern-Recognition-machine-learning/",
      "author": "Christopher M. Bishop",
      "note": "Instance-based methods and distance-based classification in a probabilistic framing."
    },
    {
      "title": "k-nearest neighbors algorithm (Wikipedia)",
      "url": "https://en.wikipedia.org/wiki/K-nearest_neighbors_algorithm",
      "author": "Wikipedia contributors",
      "note": "Overview of the algorithm, weighted k-NN, and historical references to Cover and Hart."
    }
  ]
}
