{
  "items": [
    {
      "question": "What defines self-supervised learning?",
      "options": [
        "Training only on human-labeled datasets",
        "Learning from unlabeled data using pseudo-labels derived from data structure",
        "Clustering without any loss function",
        "Reinforcement learning with environment rewards"
      ],
      "answer": "Learning from unlabeled data using pseudo-labels derived from data structure",
      "explanation": "SSL constructs pretext tasks so targets come from the data itself — masked tokens, next tokens, rotation classes, etc."
    },
    {
      "question": "In masked language modeling, the pseudo-label for a masked position is:",
      "options": [
        "A random vocabulary token",
        "The human-assigned sentiment label",
        "The original token that was masked",
        "The next sentence in the document"
      ],
      "answer": "The original token that was masked",
      "explanation": "The label already exists in the raw text; masking hides it from the input during training."
    },
    {
      "question": "Which is a text self-supervised pretext task?",
      "options": [
        "Predicting human sentiment ratings",
        "Next-token prediction on unlabeled corpus",
        "K-means on word counts",
        "Supervised image classification"
      ],
      "answer": "Next-token prediction on unlabeled corpus",
      "explanation": "The following token in the same document serves as the pseudo-label at each position."
    },
    {
      "question": "Self-supervised learning vs classic unsupervised clustering — key difference?",
      "options": [
        "SSL never uses gradients",
        "SSL always trains with a prediction loss on pseudo-labels from pretext tasks",
        "Unsupervised learning requires more labels",
        "They are identical terms"
      ],
      "answer": "SSL always trains with a prediction loss on pseudo-labels from pretext tasks",
      "explanation": "Both may use unlabeled inputs, but SSL frames an explicit surrogate prediction objective."
    },
    {
      "question": "Why do foundation models use self-supervised pretraining?",
      "options": [
        "Human labels are available for every web page",
        "Pretext tasks scale to massive unlabeled data and learn transferable representations",
        "SSL eliminates fine-tuning entirely",
        "Supervised training is always more accurate at scale"
      ],
      "answer": "Pretext tasks scale to massive unlabeled data and learn transferable representations",
      "explanation": "Web-scale text and images lack human labels; SSL learns structure first, then adapts downstream."
    }
  ]
}
