{
  "snippets": [
    {
      "title": "Hand-computed gradient in 2D",
      "language": "python",
      "code": "import numpy as np\n\ndef f(x, y):\n    return x**2 + 3 * x * y + y**2\n\ndef grad_f(x, y):\n    df_dx = 2 * x + 3 * y\n    df_dy = 3 * x + 2 * y\n    return np.array([df_dx, df_dy])\n\nx, y = 1.0, -1.0\ng = grad_f(x, y)\nprint(\"grad:\", g, \"norm:\", np.linalg.norm(g))",
      "explanation": "Partial derivatives ∂f/∂x = 2x + 3y and ∂f/∂y = 3x + 2y form the gradient vector at (1, -1)."
    },
    {
      "title": "PyTorch gradient of a scalar loss",
      "language": "python",
      "code": "import torch\n\nw = torch.tensor([2.0, -1.0], requires_grad=True)\nb = torch.tensor(0.5, requires_grad=True)\nx = torch.tensor([1.0, 2.0])\n\ny_hat = w @ x + b\nloss = (y_hat - 3.0) ** 2\nloss.backward()\n\nprint(\"grad w:\", w.grad)\nprint(\"grad b:\", b.grad)",
      "explanation": "`loss.backward()` fills `.grad` with ∂loss/∂w and ∂loss/∂b—the gradient components used for a descent update."
    },
    {
      "title": "Finite-difference check of ∇f",
      "language": "python",
      "code": "import numpy as np\n\ndef f_vec(x):\n    return x[0]**2 + 3 * x[0] * x[1] + x[1]**2\n\ndef grad_analytic(x):\n    return np.array([2 * x[0] + 3 * x[1], 3 * x[0] + 2 * x[1]])\n\ndef grad_numeric(f, x, h=1e-5):\n    g = np.zeros_like(x, dtype=float)\n    for i in range(len(x)):\n        e = np.zeros_like(x, dtype=float)\n        e[i] = h\n        g[i] = (f(x + e) - f(x - e)) / (2 * h)\n    return g\n\nx = np.array([1.0, -1.0])\nprint(np.linalg.norm(grad_analytic(x) - grad_numeric(f_vec, x)))",
      "explanation": "Coordinate-wise central differences should match analytic partials within numerical tolerance—useful when debugging custom autograd."
    }
  ]
}
