{
  "groups": [
    {
      "pattern": "comparative",
      "items": [
        {
          "question": "How does expectation differ from variance in what they summarize?",
          "answer": "E[X] is the probability-weighted center (long-run average) of X. Var(X) measures squared spread around that center—how much individual outcomes typically deviate. Two distributions can share the same mean but differ sharply in variance."
        },
        {
          "question": "When does linearity of expectation apply but variance linearity does not?",
          "answer": "E[X + Y] = E[X] + E[Y] always. Var(X + Y) = Var(X) + Var(Y) only when Cov(X, Y) = 0; with dependence, the +2 Cov(X, Y) term is required. Products also fail: E[XY] ≠ E[X]E[Y] without uncorrelated/independent assumptions."
        }
      ]
    },
    {
      "pattern": "what-if",
      "items": [
        {
          "question": "What if X and Y are independent with E[X] = 2, Var(X) = 1, E[Y] = 5, Var(Y) = 4? Find E[3X − 2Y + 1] and Var(3X − 2Y).",
          "answer": "By linearity: E[3X − 2Y + 1] = 3·2 − 2·5 + 1 = −3. For variance: Var(3X − 2Y) = 9·Var(X) + 4·Var(Y) = 9·1 + 4·4 = 25 (independence ⇒ Cov = 0)."
        },
        {
          "question": "What if a model's validation RMSE is 10 but individual errors are heavy-tailed?",
          "answer": "RMSE ≈ √(E[squared error]) is sensitive to large outliers because variance weights big errors quadratically. A similar MAE might be much smaller, signaling occasional huge mistakes—reporting mean error alone would miss that tail behavior."
        }
      ]
    }
  ]
}
