{
  "items": [
    {
      "title": "Python docs — tracemalloc",
      "url": "https://docs.python.org/3/library/tracemalloc.html",
      "note": "Canonical reference; snapshots, statistics, compare_to, frame depth."
    },
    {
      "title": "memray — Bloomberg's Python memory profiler",
      "url": "https://bloomberg.github.io/memray/",
      "note": "Flamegraphs, leak-suspects view, live mode; the modern flagship Python memory tool."
    },
    {
      "title": "psutil",
      "url": "https://psutil.readthedocs.io/",
      "note": "Cross-platform RSS/CPU/IO metrics; the easy first-look tool."
    },
    {
      "title": "Python — gc module",
      "url": "https://docs.python.org/3/library/gc.html",
      "note": "Understand what `gc.collect()` does (and doesn't) before reaching for it."
    },
    {
      "title": "Doug Hellmann — tracemalloc tutorial",
      "url": "https://pymotw.com/3/tracemalloc/",
      "note": "Worked examples for snapshots and diffs; great as a first hands-on guide."
    }
  ]
}
