{
  "items": [
    {
      "title": "pip & requirements.txt",
      "relation": "contrasts with",
      "description": "Poetry replaces the manual pip + requirements.txt workflow with declarative pyproject.toml and a solver-backed lockfile.",
      "topicId": "dependency-management--pip-and-requirements-txt"
    },
    {
      "title": "Lockfiles & Reproducibility",
      "relation": "builds on",
      "description": "poetry.lock is a concrete example of a lockfile guaranteeing reproducible installs.",
      "topicId": "dependency-management--lockfiles-and-reproducibility"
    },
    {
      "title": "venv & virtualenv",
      "relation": "automates",
      "description": "Poetry creates and manages a virtual environment for you instead of manual venv activation.",
      "topicId": "dependency-management--venv-and-virtualenv"
    }
  ]
}
