{
  "items": [
    {
      "question": "Which metric should primarily drive checkpoint selection during training?",
      "options": [
        "train/accuracy",
        "val/f1 or val/loss on held-out data",
        "test/f1 logged every epoch",
        "train/loss only"
      ],
      "answer": "val/f1 or val/loss on held-out data",
      "explanation": "Validation metrics estimate generalization during development; train metrics overstate fit and test metrics should not be used iteratively."
    },
    {
      "question": "What naming pattern best distinguishes metrics by data split?",
      "options": [
        "loss, accuracy, f1 without prefixes",
        "train/loss, val/loss, test/f1",
        "metric1, metric2, metric3",
        "final_score only"
      ],
      "answer": "train/loss, val/loss, test/f1",
      "explanation": "Split prefixes (train/, val/, test/) make curves comparable and reveal train vs validation divergence."
    },
    {
      "question": "Train/loss keeps decreasing but val/loss rises after epoch 20. What does this suggest?",
      "options": ["Underfitting", "Overfitting", "Broken random seed", "Need more train metrics"],
      "answer": "Overfitting",
      "explanation": "Improving train loss with worsening validation loss is the classic overfitting signature on scalar curves."
    },
    {
      "question": "When should test/f1 typically be logged?",
      "options": [
        "Every training step",
        "Every epoch alongside val/f1",
        "Once after selecting the best validation checkpoint",
        "Only in production after deployment"
      ],
      "answer": "Once after selecting the best validation checkpoint",
      "explanation": "Test metrics are for final sign-off— logging them every epoch invites test-set-driven selection."
    }
  ]
}
